cenroc/__init__.py
cenroc/cenroc.py
cenroc-0.0.6.dist-info/METADATA
cenroc-0.0.6.dist-info/WHEEL
cenroc-0.0.6.dist-info/top_level.txt
cenroc-0.0.6.dist-info/RECORD
